wintree/__init__.py
wintree/cli.py
wintree-0.1.17.dist-info/entry_points.txt
wintree-0.1.17.dist-info/LICENSE
wintree-0.1.17.dist-info/METADATA
wintree-0.1.17.dist-info/WHEEL
wintree-0.1.17.dist-info/RECORD
