Metadata-Version: 2.3
Name: wintree
Version: 0.1.17
Summary: A lightweight Python library and CLI tool for displaying visually structured directory trees with optional emoji and exclusion filters.
License: MIT
Author: harumiWeb
Requires-Python: >=3.12,<4.0
Classifier: License :: OSI Approved :: MIT License
Classifier: Programming Language :: Python :: 3
Classifier: Programming Language :: Python :: 3.12
Classifier: Programming Language :: Python :: 3.13
Project-URL: Repository, https://github.com/harumiWeb/wintree
